[ { "text": "Fútbol 1 (Camisetas, Sudaderas, Abrigos)", "url": "https://topfootballjersey.x.yupoo.com/categories", "img": "imagenes/ropa/ropa-1.png" },
  { "text": "Fútbol 2 (Camisetas, Conjuntos)", "url": "https://x.yupoo.com/photos/1022669895/categories", "img": "imagenes/ropa/ropa-2.png" },
  { "text": "Fútbol 3", "url": "https://xingfeng001.x.yupoo.com/categories", "img": "imagenes/ropa/ropa-3.png" },
  { "text": "Fútbol 4", "url": "https://junhaoqiumi.x.yupoo.com/categories", "img": "imagenes/ropa/ropa-4.png" },
  { "text": "Fútbol 5", "url": "https://239373382.x.yupoo.com/categories", "img": "imagenes/ropa/ropa-5.png" },
  { "text": "Fútbol Niño Conjuntos 1", "url": "https://1022669895.x.yupoo.com/categories/3860619", "img": "imagenes/ropa/ropa-6.png" },
  { "text": "Fútbol Niño Conjuntos 2", "url": "https://xyfs1688.x.yupoo.com/categories", "img": "imagenes/ropa/ropa-7.png" },
  { "text": "Fútbol Niño Conjuntos 3", "url": "https://ao-sheng.x.yupoo.com/categories", "img": "imagenes/ropa/ropa-8.png" },
  { "text": "Fútbol Niño Conjuntos 4", "url": "https://xiaoyueliang0917.x.yupoo.com/categories", "img": "imagenes/ropa/ropa-9.png" },
  { "text": "Fútbol Niño Conjuntos 5", "url": "https://tz583276982.x.yupoo.com/categories", "img": "imagenes/ropa/ropa-10.png" },
  { "text": "Fútbol Niño Conjuntos 6", "url": "https://xingfeng001.x.yupoo.com/categories/4583569", "img": "imagenes/ropa/ropa-11.png" },
  { "text": "Fútbol Niño Conjuntos 7 (Clave: 1234567)", "url": "https://ouyu123.x.yupoo.com/categories", "img": "imagenes/ropa/ropa-12.png" },
  { "text": "Fútbol Ropa Bebe 1", "url": "https://topfootballjersey.x.yupoo.com/categories/4589192", "img": "imagenes/ropa/ropa-13.png" },
  { "text": "Fútbol Ropa Bebe 2", "url": "https://xingfeng001.x.yupoo.com/categories/4583568", "img": "imagenes/ropa/ropa-14.png" },
  { "text": "Fútbol Camiseta Fans", "url": "https://yongfa1688.x.yupoo.com/categories", "img": "imagenes/ropa/ropa-15.png" },
  { "text": "Fútbol Camiseta Versión Jugador 1 ", "url": "https://baocheng3f888.x.yupoo.com/categories", "img": "imagenes/ropa/ropa-16.png" },
  { "text": "Fútbol Camiseta Versión Jugador 2", "url": "https://yexinyundong.x.yupoo.com/categories", "img": "imagenes/ropa/ropa-17.png" },
  { "text": "Fútbol Camiseta Versión Jugador 3", "url": "https://3409834285.x.yupoo.com/categories", "img": "imagenes/ropa/ropa-18.png" },
  { "text": "Fútbol Camiseta Retro 1", "url": "https://huiliyuan.x.yupoo.com/categories", "img": "imagenes/ropa/ropa-19.png" },
  { "text": "Fútbol Camiseta Retro 2", "url": "https://lt-juncheng888.x.yupoo.com/categories", "img": "imagenes/ropa/ropa-20.png" },
  { "text": "Fútbol Camiseta Retro 3", "url": "https://shida-sports888.x.yupoo.com/categories", "img": "imagenes/ropa/ropa-21.png" },
  { "text": "Fútbol Entrenamiento 1", "url": "https://huang456852.x.yupoo.com/categories", "img": "imagenes/ropa/ropa-22.png" },
  { "text": "Fútbol Entrenamiento 2", "url": "https://007007haoyuntiyu.x.yupoo.com/categories", "img": "imagenes/ropa/ropa-23.png" },
  { "text": "Fútbol Entrenamiento 3", "url": "https://dongshanstore.x.yupoo.com/categories", "img": "imagenes/ropa/ropa-24.png" },
  { "text": "Fútbol Entrenamiento 4", "url": "https://x.yupoo.com/photos/changjiangsports/categories", "img": "imagenes/ropa/ropa-25.png" },
  { "text": "Fútbol Entrenamiento 5", "url": "https://aosendi.x.yupoo.com/categories", "img": "imagenes/ropa/ropa-26.png" },
  { "text": "Fútbol Entrenamiento 6", "url": "https://huang456852.x.yupoo.com/collections/2887577", "img": "imagenes/ropa/ropa-27.png" },
  { "text": "Fútbol Entrenamiento de Tirantes 7", "url": "https://huang456852.x.yupoo.com/collections/3883976", "img": "imagenes/ropa/ropa-28.png" },
  { "text": "Fútbol Entrenamiento de Capucha 8", "url": "https://huang456852.x.yupoo.com/collections/4730493", "img": "imagenes/ropa/ropa-29.png" },
  { "text": "Fútbol Entrenamiento 9", "url": "https://007007haoyuntiyu.x.yupoo.com/collections/4742233", "img": "imagenes/ropa/ropa-30.png" },
  { "text": "Fútbol Entrenamiento 10", "url": "https://dongshanstore.x.yupoo.com/categories/322329", "img": "imagenes/ropa/ropa-31.png" },
  { "text": "Fútbol Entrenamiento Niño 7", "url": "https://dongshanstore.x.yupoo.com/categories/322330", "img": "imagenes/ropa/ropa-32.png" },
  { "text": "Ropa Variada Verano-Invierno 1", "url": "https://ty-guoji.x.yupoo.com/categories", "img": "imagenes/ropa/ropa-33.png" },
  { "text": "Ropa Variada Verano-Deportivo 2", "url": "https://3179704378.x.yupoo.com/categories", "img": "imagenes/ropa/ropa-34.png" },
  { "text": "Ropa Variada Verano-Invierno 3", "url": "https://ty-guoji2.x.yupoo.com/categories", "img": "imagenes/ropa/ropa-35.png" },
  { "text": "Ropa Variada Verano-Invierno 4", "url": "https://ting8899.x.yupoo.com/categories", "img": "imagenes/ropa/ropa-36.png" },
  { "text": "Ropa Variada Verano-Deportivo 5", "url": "https://lisa1059.x.yupoo.com/categories", "img": "imagenes/ropa/ropa-37.png" },
  { "text": "Cortavientos & Chaquetones 1", "url": "https://www9900.x.yupoo.com/categories", "img": "imagenes/ropa/ropa-38.png" },
  { "text": "Cortavientos & Chaquetones 2", "url": "https://1215795243.x.yupoo.com/", "img": "imagenes/ropa/ropa-39.png" },
  { "text": "Cortavientos & Chaquetones 3", "url": "https://dl-cfy666.x.yupoo.com/categories", "img": "imagenes/ropa/ropa-40.png" },
  { "text": "Zapatillas Casual 1", "url": "https://zq-8866.x.yupoo.com/categories", "img": "imagenes/ropa/ropa-41.png" },
  { "text": "Zapatillas Casual 2", "url": "https://al413666.x.yupoo.com/categories", "img": "imagenes/ropa/ropa-42.png" },
  { "text": "Zapatillas Casual 3", "url": "https://chizudengyue.x.yupoo.com/categories", "img": "imagenes/ropa/ropa-43.png" },
  { "text": "Zapatillas Casual 4", "url": "https://x.yupoo.com/photos/forester-sports/categories", "img": "imagenes/ropa/ropa-44.png" },
  { "text": "Zapatillas Casual 5", "url": "https://xueli860923.x.yupoo.com/categories", "img": "imagenes/ropa/ropa-45.png" },
  { "text": "Zapatillas Casual 6", "url": "https://dadivsmaoyi.x.yupoo.com/categories", "img": "imagenes/ropa/ropa-46.png" },
  { "text": "Zapatillas Casual 7 (Clave: 112288)", "url": "https://aj-dongli.x.yupoo.com/categories", "img": "imagenes/ropa/ropa-47.png" },
  { "text": "Zapatillas Casual 8", "url": "https://lifengshoes.x.yupoo.com/categories", "img": "imagenes/ropa/ropa-48.png" },
  { "text": "Zapatillas Fútbol 1", "url": "https://dachang88.x.yupoo.com/categories", "img": "imagenes/ropa/ropa-49.png" },
  { "text": "Zapatillas Fútbol 2", "url": "https://yehecheng.x.yupoo.com/categories", "img": "imagenes/ropa/ropa-50.png" },
  { "text": "Zapatillas Fútbol 3", "url": "https://lyzs88.x.zhidian-inc.cn/categories", "img": "imagenes/ropa/ropa-51.png" },
  { "text": "Zapatillas Niños 1", "url": "https://qiumitiantang.x.yupoo.com/categories", "img": "imagenes/ropa/ropa-52.png" },
  { "text": "Zapatillas Niños 2", "url": "https://017017.x.yupoo.com/categories", "img": "imagenes/ropa/ropa-53.png" },
  { "text": "Zapatillas Niños 3", "url": "https://zhaomin1981.x.yupoo.com/albums", "img": "imagenes/ropa/ropa-54.png" },
  { "text": "Zapatillas Niños 4", "url": "https://lyck.x.yupoo.com/albums", "img": "imagenes/ropa/ropa-55.png" },
  { "text": "Zapatillas Baloncesto 1", "url": "https://zylq1688.x.yupoo.com/categories", "img": "imagenes/ropa/ropa-56.png" },
  { "text": "Zapatillas Baloncesto 2", "url": "https://18666.x.yupoo.com/categories", "img": "imagenes/ropa/ropa-57.png" },
  { "text": "Deportes del Mundo", "url": "https://yiyisports2016.x.yupoo.com/categories", "img": "imagenes/ropa/ropa-58.png" },
  { "text": "F1 Camisetas 1", "url": "https://topfootballjersey.x.yupoo.com/categories/4589217", "img": "imagenes/ropa/ropa-59.png" },
  { "text": "F1 Camisetas 2", "url": "https://xingfeng001.x.yupoo.com/categories/4583584", "img": "imagenes/ropa/ropa-60.png" },
  { "text": "NFL & MLB 1", "url": "https://kk6666.x.yupoo.com/categories", "img": "imagenes/ropa/ropa-61.png" },
  { "text": "NFL & MLB 2", "url": "https://eryiqiuyi111.x.yupoo.com/categories", "img": "imagenes/ropa/ropa-62.png" },
  { "text": "NFL & MLB 3", "url": "https://topfootballjersey.x.yupoo.com/categories/4589216", "img": "imagenes/ropa/ropa-63.png" },
  { "text": "NBA 1 Tirantes", "url": "https://dongshanstore.x.yupoo.com/categories/3498460", "img": "imagenes/ropa/ropa-64.png" },
  { "text": "NBA 2 Camisetas", "url": "https://xingkong-sports.x.yupoo.com/categories", "img": "imagenes/ropa/ropa-65.png" },
  { "text": "NBA 3 Variado", "url": "https://www696688.x.yupoo.com/categories", "img": "imagenes/ropa/ropa-66.png" },
  { "text": "NBA 4 Variado", "url": "https://topfootballjersey.x.yupoo.com/categories/4589215", "img": "imagenes/ropa/ropa-67.png" },
  { "text": "NBA 5 Equipos", "url": "https://xingfeng001.x.yupoo.com/categories/4583580", "img": "imagenes/ropa/ropa-68.png" },
  { "text": "NBA 6 Sudaderas", "url": "https://8888weiyi.x.yupoo.com/categories", "img": "imagenes/ropa/ropa-69.png" },
  { "text": "NBA 7 Tirantes", "url": "https://topfootballjersey.x.yupoo.com/categories/4589223", "img": "imagenes/ropa/ropa-70.png" },
  { "text": "NBA 8 Tirantes", "url": "https://topfootballjersey.x.yupoo.com/categories/4589225", "img": "imagenes/ropa/ropa-71.png" },
  { "text": "NBA 9 Chaquetones", "url": "https://dongshanstore.x.yupoo.com/categories/3217172", "img": "imagenes/ropa/ropa-72.png" },
  { "text": "Gorras y más (Clave: 668899)", "url": "https://lin881106.x.yupoo.com/categories", "img": "imagenes/ropa/ropa-73.png" },
  { "text": "Bolsas, Mochilas, Riñoneras y más 1", "url": "https://mysport8899.x.yupoo.com/categories", "img": "imagenes/ropa/ropa-74.png" },
  { "text": "Bolsas, Mochilas, Riñoneras y más 2", "url": "https://pang2017.x.yupoo.com/categories", "img": "imagenes/ropa/ropa-75.png" },
  { "text": "KING LEAGUE", "url": "https://topfootballjersey.x.yupoo.com/categories/4589199", "img": "imagenes/ropa/ropa-76.png" },
  { "text": "Ropa de Marca Cara", "url": "https://pikachu01.x.yupoo.com/categories", "img": "imagenes/ropa/ropa-77.png" },
  { "text": "Personalizacion Ropa Equipo Fútbol", "url": "https://topfootballjersey.x.yupoo.com/categories/4589185", "img": "imagenes/ropa/ropa-78.png" }

]
